{"name": "TuyaSmartResidenceKit", "version": "1.2.1-feature-1.2.1.1", "summary": "A short description of TuyaSmartResidenceKit.", "description": "TODO: Add long description of the pod here.", "homepage": "https://developer.tuya.com/", "license": {"type": "MIT", "file": "LICENSE"}, "authors": {"Tuya": "developer@tuya.com"}, "source": {"http": "https://images.tuyacn.com/smart/app/package/developer/sdk/1708918188-TuyaSmartResidenceKit-1.2.1-feature-1.2.1.1.zip", "type": "zip"}, "platforms": {"ios": "9.0"}, "dependencies": {"TuyaSmartBaseKit": [], "TuyaSmartActivatorCoreKit": []}, "vendored_frameworks": ["Build/TuyaSmartResidenceKit.xcframework"], "source_files": ["Build/TuyaSmartResidenceKit.xcframework/ios-arm64/TuyaSmartResidenceKit.framework/Headers/*"]}