{
  "name": "ThingMiniAppTabModule",
  "version": "2.5.0",
  "summary": "A short description of ThingMiniAppTabModule.",
  "homepage": "https://github.com/tuya",
  "license": "none",
  "authors": {
    "TuyaInc": "https://developer.tuya.com/"
  },
  "source": {
    "http": "https://images.tuyacn.com/smart/app/package/pods/ios/ThingMiniAppTabModule-2.5.0-ddc14f.zip",
    "type": "zip",
    "sha1": "a8ec9cdaaabbec5a78dcdbb0540285ad14c519ac"
  },
  "platforms": {
    "ios": "11.0"
  },
  "dependencies": {
    "ThingModuleServices": [

    ],
    "ThingModuleManager": [

    ],
    "YYModel": [

    ],
    "ThingOEMConfig": [

    ],
    "ThingNavigationController": [

    ],
    "ThingPanelDynamicContainerAPI": [

    ],
    "ThingDynamicContainerPlugin": [

    ],
    "GodzillaMiniBaseKit": [

    ]
  },
  "pod_target_xcconfig": {
    "EXCLUDED_ARCHS[sdk=iphonesimulator*]": "arm64",
    "EXCLUDED_ARCHS[sdk=watchsimulator*]": "x86_64 arm64"
  },
  "user_target_xcconfig": {
    "EXCLUDED_ARCHS[sdk=iphonesimulator*]": "arm64",
    "EXCLUDED_ARCHS[sdk=watchsimulator*]": "x86_64 arm64"
  },
  "preserve_paths": [

  ],
  "vendored_frameworks": [
    "ThingMiniAppTabModule.xcframework"
  ],
  "cocoapods_version": ">= 1.10"
}
