{
  "name": "TUNIMediaKit",
  "version": "3.2.2",
  "summary": "涂鸦TTT(Tuya Tied Things ) group 插件集合",
  "homepage": "https://github.com/tuya",
  "license": "none",
  "authors": {
    "TuyaInc": "https://developer.tuya.com/"
  },
  "platforms": {
    "ios": "11.0"
  },
  "source": {
    "http": "https://images.tuyacn.com/smart/app/package/pods/ios/TUNIMediaKit-3.2.2.1-e5532b.zip",
    "type": "zip",
    "sha1": "7c295633bc14c35a00ad869f09ddd83bdd8fe6ca"
  },
  "resource_bundles": {
    "TUNIMediaKit": [
      "ios/TUNIMediaKit/Assets/*"
    ]
  },
  "dependencies": {
    "TUNIDLCameraManager": [
      "3.0.5"
    ],
    "TUNIDLVideoManager": [
      "3.3.2"
    ],
    "TUNIMusicManager": [
      "1.1.0-rc.9"
    ]
  },
  "vendored_frameworks": [
    "TUNIMediaKit.xcframework"
  ],
  "cocoapods_version": ">= 1.10"
}
