{"name": "IndustryDeviceKit", "version": "2.3.0", "summary": "A short description of IndustryDeviceKit.", "description": "TODO: Add long description of the pod here.", "homepage": "https://developer.tuya.com/", "license": {"type": "MIT", "file": "LICENSE"}, "authors": {"Tuya": "developer@tuya.com"}, "source": {"http": "https://images.tuyacn.com/smart/app/package/developer/sdk/1725016918-IndustryDeviceKit-2.3.0.zip", "type": "zip"}, "platforms": {"ios": "10.0"}, "swift_versions": "5.6", "static_framework": true, "dependencies": {"IotContainer": [], "IndustryErrorKit": [], "ThingSmartUtil": []}, "xcconfig": {"OTHER_SWIFT_FLAGS": "-no-verify-emitted-module-interface"}, "pod_target_xcconfig": {"DEFINES_MODULE": "YES", "BUILD_LIBRARY_FOR_DISTRIBUTION": "YES", "CLANG_ALLOW_NON_MODULAR_INCLUDES_IN_FRAMEWORK_MODULES": "YES"}, "vendored_frameworks": ["Build/IndustryDeviceKit.xcframework"], "source_files": ["Build/IndustryDeviceKit.xcframework/ios-arm64/IndustryDeviceKit.framework/Headers/*"], "swift_version": "5.6"}