{
    "authors": {
        "TuyaInc": "https://developer.tuya.com/"
    },
    "cocoapods_version": ">= 1.10",
    "dependencies": {
        "TUNIAPIManagerKit": [],
        "YYModel": []
    },
    "description": "TODO: Add long description of the pod here.",
    "frameworks": [
        "AudioToolbox",
        "UIKit"
    ],
    "homepage": "https://github.com/tuya",
    "license": "none",
    "name": "TUNIPhoneVibrateManager",
    "platforms": {
        "ios": "9.0"
    },
    "pod_target_xcconfig": {
        "EXCLUDED_ARCHS[sdk=iphonesimulator*]": "arm64",
        "EXCLUDED_ARCHS[sdk=watchsimulator*]": "x86_64 arm64"
    },
    "source": {
        "http": "https://airtake-public-data-1254153901.cos.ap-shanghai.myqcloud.com/smart/app/package/pods/ios/TUNIPhoneVibrateManager-1.0.1-anonymize.2.zip",
        "type": "zip"
    },
    "summary": "A short description of TUNIPhoneVibrateManager.",
    "user_target_xcconfig": {
        "EXCLUDED_ARCHS[sdk=iphonesimulator*]": "arm64",
        "EXCLUDED_ARCHS[sdk=watchsimulator*]": "x86_64 arm64"
    },
    "vendored_frameworks": [
        "TUNIPhoneVibrateManager.xcframework"
    ],
    "version": "1.0.1-anonymize.2"
}