{
  "name": "TUNIRouterManager",
  "version": "2.2.0",
  "summary": "A short description of TUNIRouterManager.",
  "homepage": "https://github.com/tuya",
  "license": "none",
  "authors": {
    "TuyaInc": "https://developer.tuya.com/"
  },
  "source": {
    "http": "https://images.tuyacn.com/smart/app/package/pods/ios/TUNIRouterManager-2.2.0-e8de89.zip",
    "type": "zip",
    "sha1": "fe42d2d0c1d336bdfaf46eb64d3ab862a52d3594"
  },
  "platforms": {
    "ios": "11.0"
  },
  "resource_bundles": {
    "TUNIRouterManager": [
      "ios/tuniroutermanager/Assets/*"
    ]
  },
  "dependencies": {
    "TUNIAPIManagerKit": [

    ],
    "YYModel": [

    ],
    "ThingModuleManager": [

    ],
    "ThingDeviceTimerPlugAPI": [

    ],
    "ThingDeviceDetailPlugAPI": [

    ],
    "ThingSmartDeviceCoreKit": [

    ]
  },
  "pod_target_xcconfig": {
    "EXCLUDED_ARCHS[sdk=iphonesimulator*]": "arm64",
    "EXCLUDED_ARCHS[sdk=watchsimulator*]": "x86_64 arm64"
  },
  "user_target_xcconfig": {
    "EXCLUDED_ARCHS[sdk=iphonesimulator*]": "arm64",
    "EXCLUDED_ARCHS[sdk=watchsimulator*]": "x86_64 arm64"
  },
  "vendored_frameworks": [
    "TUNIRouterManager.xcframework"
  ],
  "cocoapods_version": ">= 1.10"
}
