{
  "name": "TUNIUploadFileManager",
  "version": "1.4.3",
  "summary": "A short description of TUNIUploadFileManager.",
  "homepage": "https://github.com/tuya",
  "license": "none",
  "authors": {
    "TuyaInc": "https://developer.tuya.com/"
  },
  "source": {
    "http": "https://images.tuyacn.com/smart/app/package/pods/ios/TUNIUploadFileManager-1.4.3.1.zip",
    "type": "zip",
    "sha1": "77d42d245d32517168a14602b5be637bdc93385d"
  },
  "platforms": {
    "ios": "9.0"
  },
  "resource_bundles": {
    "TUNIUploadFileManager": [
      "ios/TUNIUploadFileManager/Assets/*",
      "js/dist/index.js"
    ]
  },
  "dependencies": {
    "TUNIAPIManagerKit": [

    ],
    "YYModel": [

    ]
  },
  "pod_target_xcconfig": {
    "EXCLUDED_ARCHS[sdk=iphonesimulator*]": "arm64",
    "EXCLUDED_ARCHS[sdk=watchsimulator*]": "x86_64 arm64"
  },
  "user_target_xcconfig": {
    "EXCLUDED_ARCHS[sdk=iphonesimulator*]": "arm64",
    "EXCLUDED_ARCHS[sdk=watchsimulator*]": "x86_64 arm64"
  },
  "vendored_frameworks": [
    "TUNIUploadFileManager.xcframework"
  ],
  "cocoapods_version": ">= 1.10"
}
