{
  "name": "ThingDeviceTimerPlugAPI",
  "version": "0.2.0",
  "summary": "A short description of ThingDeviceTimerPlugAPI.",
  "homepage": "https://github.com/tuya",
  "license": "none",
  "authors": {
    "TuyaInc": "https://developer.tuya.com/"
  },
  "source": {
    "http": "https://images.tuyacn.com/smart/app/package/pods/ios/ThingDeviceTimerPlugAPI-0.2.0.1-23bf5c.zip",
    "type": "zip",
    "sha1": "6079794bb092ac619e5cceaea38a59d9da049aeb"
  },
  "platforms": {
    "ios": "9.0"
  },
  "dependencies": {
    "ThingSmartTimerKit": [

    ]
  },
  "pod_target_xcconfig": {
    "EXCLUDED_ARCHS[sdk=iphonesimulator*]": "arm64",
    "EXCLUDED_ARCHS[sdk=watchsimulator*]": "x86_64 arm64"
  },
  "user_target_xcconfig": {
    "EXCLUDED_ARCHS[sdk=iphonesimulator*]": "arm64",
    "EXCLUDED_ARCHS[sdk=watchsimulator*]": "x86_64 arm64"
  },
  "vendored_frameworks": [
    "ThingDeviceTimerPlugAPI.xcframework"
  ],
  "cocoapods_version": ">= 1.10"
}
