{
  "name": "ThingHybridMall",
  "version": "1.11.2",
  "summary": "A short description of ThingHybridMall.",
  "homepage": "https://github.com/tuya",
  "license": "none",
  "authors": {
    "TuyaInc": "https://developer.tuya.com/"
  },
  "source": {
    "http": "https://images.tuyacn.com/smart/app/package/pods/ios/ThingHybridMall-1.11.2-4d23a1.zip",
    "type": "zip",
    "sha1": "2ff9b89535290316af7cd31f1e21c5685b94b05e"
  },
  "platforms": {
    "ios": "11.0"
  },
  "dependencies": {
    "ThingModuleManager": [

    ],
    "ThingModuleServices": [

    ],
    "ThingHybridContainer": [

    ],
    "ThingUrlPredefined": [

    ],
    "ThingSmartBaseKit": [

    ],
    "ThingOEMConfig": [

    ],
    "ThingKVStorageLibrary": [

    ],
    "YYModel": [

    ]
  },
  "pod_target_xcconfig": {
    "EXCLUDED_ARCHS[sdk=iphonesimulator*]": "arm64",
    "EXCLUDED_ARCHS[sdk=watchsimulator*]": "x86_64 arm64"
  },
  "user_target_xcconfig": {
    "EXCLUDED_ARCHS[sdk=iphonesimulator*]": "arm64",
    "EXCLUDED_ARCHS[sdk=watchsimulator*]": "x86_64 arm64"
  },
  "preserve_paths": "weak_deps.json",
  "vendored_frameworks": [
    "ThingHybridMall.xcframework"
  ],
  "cocoapods_version": ">= 1.10"
}
