{
  "name": "RNCMaskedView",
  "version": "0.1.10.1",
  "summary": "React Native MaskedView component",
  "license": "none",
  "authors": {
    "TuyaInc": "https://developer.tuya.com/"
  },
  "homepage": "https://github.com/tuya",
  "platforms": {
    "ios": "9.0"
  },
  "source": {
    "http": "https://images.tuyacn.com/smart/app/package/pods/ios/RNCMaskedView-0.1.10.1.1-297533.zip",
    "type": "zip",
    "sha1": "5d6854a67a0ae4b63cfa9a0dd18d8cb6d36cfda9"
  },
  "dependencies": {
    "React": [

    ]
  },
  "vendored_frameworks": [
    "RNCMaskedView.xcframework"
  ],
  "cocoapods_version": ">= 1.10"
}
