{
  "name": "ThingOEMConfig",
  "version": "1.60.4.2",
  "summary": "OEM打包配置项",
  "homepage": "https://github.com/tuya",
  "license": "none",
  "authors": {
    "TuyaInc": "https://developer.tuya.com/"
  },
  "source": {
    "http": "https://images.tuyacn.com/smart/app/package/pods/ios/ThingOEMConfig-1.60.4.2-77e884.zip",
    "type": "zip",
    "sha1": "b3da88b03590dc7a87b22b210f7274c90dcfb8e7"
  },
  "platforms": {
    "ios": "11.0",
    "watchos": "2.0"
  },
  "ios": {
    "dependencies": {
      "ThingKVStorageLibrary": [

      ]
    }
  },
  "watchos": {
    "pod_target_xcconfig": {
      "ENABLE_BITCODE": "NO",
      "OTHER_CFLAGS": "-fembed-bitcode -Qunused-arguments"
    }
  },
  "dependencies": {
    "YYModel": [

    ],
    "ThingSmartBaseKit": [

    ],
    "ThingFoundationKit": [

    ],
    "ThingEncryptImage": [

    ],
    "libextobjc": [

    ],
    "ThingMachRegister": [

    ],
    "ThingSettingsAPI": [

    ]
  },
  "pod_target_xcconfig": {
    "DEFINES_MODULE": "YES"
  },
  "preserve_paths": [

  ],
  "vendored_frameworks": [
    "ThingOEMConfig.xcframework"
  ],
  "cocoapods_version": ">= 1.10"
}
